genebot/__init__.py
genebot/cli.py
genebot/analysis/__init__.py
genebot/analysis/arbitrage_detector.py
genebot/cli/__init__.py
genebot/cli/__main__.py
genebot/cli/context.py
genebot/cli/error_handler.py
genebot/cli/main.py
genebot/cli/parser.py
genebot/cli/result.py
genebot/cli/commands/__init__.py
genebot/cli/commands/account.py
genebot/cli/commands/base.py
genebot/cli/commands/bot.py
genebot/cli/commands/cli_test.py
genebot/cli/commands/completion.py
genebot/cli/commands/config.py
genebot/cli/commands/database_test.py
genebot/cli/commands/error_report.py
genebot/cli/commands/final_validation.py
genebot/cli/commands/live_trading.py
genebot/cli/commands/monitoring.py
genebot/cli/commands/orchestrator.py
genebot/cli/commands/orchestrator_migration.py
genebot/cli/commands/performance.py
genebot/cli/commands/router.py
genebot/cli/commands/security.py
genebot/cli/commands/system_health.py
genebot/cli/commands/trading_test.py
genebot/cli/commands/utility.py
genebot/cli/commands/validate.py
genebot/cli/utils/__init__.py
genebot/cli/utils/account_manager.py
genebot/cli/utils/account_validator.py
genebot/cli/utils/completion.py
genebot/cli/utils/config_manager.py
genebot/cli/utils/data_manager.py
genebot/cli/utils/dependency_checker.py
genebot/cli/utils/dependency_mixin.py
genebot/cli/utils/dependency_validator.py
genebot/cli/utils/error_handler.py
genebot/cli/utils/error_recovery.py
genebot/cli/utils/file_manager.py
genebot/cli/utils/formatting.py
genebot/cli/utils/installation_guide.py
genebot/cli/utils/integration_manager.py
genebot/cli/utils/logger.py
genebot/cli/utils/output_manager.py
genebot/cli/utils/process_manager.py
genebot/cli/utils/security_manager.py
genebot/cli/utils/validator.py
genebot/config/__init__.py
genebot/config/logging.py
genebot/config/manager.py
genebot/config/models.py
genebot/config/validation_utils.py
genebot/core/__init__.py
genebot/core/__main__.py
genebot/core/orchestrator.py
genebot/core/runner.py
genebot/core/trading_bot.py
genebot-1.1.42.dist-info/METADATA
genebot-1.1.42.dist-info/WHEEL
genebot-1.1.42.dist-info/entry_points.txt
genebot-1.1.42.dist-info/top_level.txt
genebot-1.1.42.dist-info/RECORD
