Metadata-Version: 2.4
Name: genebot
Version: 1.1.42
Summary: Advanced Multi-Market Trading Bot with Crypto & Forex Support
Author-email: GeneBot Development Team <support@genebot.ai>
Maintainer-email: GeneBot Core Team <maintainers@genebot.ai>
License-Expression: MIT
Project-URL: Homepage, https://github.com/genebot/genebot
Project-URL: Documentation, https://docs.genebot.ai
Project-URL: Repository, https://github.com/genebot/genebot.git
Project-URL: Bug Tracker, https://github.com/genebot/genebot/issues
Project-URL: Feature Requests, https://github.com/genebot/genebot/discussions
Project-URL: Changelog, https://github.com/genebot/genebot/blob/main/CHANGELOG.md
Project-URL: Release Notes, https://github.com/genebot/genebot/releases
Project-URL: Security Policy, https://github.com/genebot/genebot/security/policy
Project-URL: Contributing, https://github.com/genebot/genebot/blob/main/CONTRIBUTING.md
Project-URL: Code of Conduct, https://github.com/genebot/genebot/blob/main/CODE_OF_CONDUCT.md
Keywords: trading,bot,crypto,forex,algorithmic-trading,multi-market,risk-management,backtesting,portfolio,arbitrage,strategy,automation,finance,investment
Classifier: Development Status :: 4 - Beta
Classifier: Intended Audience :: Financial and Insurance Industry
Classifier: Topic :: Office/Business :: Financial :: Investment
Classifier: Programming Language :: Python :: 3
Classifier: Programming Language :: Python :: 3.8
Classifier: Programming Language :: Python :: 3.9
Classifier: Programming Language :: Python :: 3.10
Classifier: Programming Language :: Python :: 3.11
Classifier: Programming Language :: Python :: 3.12
Classifier: Operating System :: OS Independent
Requires-Python: >=3.8
Requires-Dist: ccxt>=4.0.0
Requires-Dist: pandas>=1.5.0
Requires-Dist: numpy>=1.21.0
Requires-Dist: pydantic>=2.0.0
Requires-Dist: PyYAML>=6.0
Requires-Dist: python-dotenv>=1.0.0
Requires-Dist: requests>=2.28.0
Requires-Dist: aiohttp>=3.8.0
Requires-Dist: websockets>=11.0
Requires-Dist: sqlalchemy>=2.0.0
Requires-Dist: alembic>=1.12.0
Requires-Dist: colorama>=0.4.6
Requires-Dist: tabulate>=0.9.0
Requires-Dist: rich>=13.0.0
Requires-Dist: click>=8.0.0
Requires-Dist: matplotlib>=3.6.0
Requires-Dist: seaborn>=0.12.0
Requires-Dist: scipy>=1.9.0
Requires-Dist: TA-Lib>=0.4.25
Requires-Dist: yfinance>=0.2.0
Requires-Dist: psutil>=5.9.0
Requires-Dist: asyncio-mqtt>=0.13.0
Requires-Dist: structlog>=23.0.0
Requires-Dist: cryptography>=41.0.0
Provides-Extra: dev
Requires-Dist: pytest>=7.0; extra == "dev"
Requires-Dist: pytest-asyncio>=0.21.0; extra == "dev"
Requires-Dist: pytest-cov>=4.0; extra == "dev"
Requires-Dist: pytest-mock>=3.10; extra == "dev"
Requires-Dist: pytest-xdist>=3.0; extra == "dev"
Requires-Dist: black>=23.0; extra == "dev"
Requires-Dist: ruff>=0.1.0; extra == "dev"
Requires-Dist: mypy>=1.5; extra == "dev"
Requires-Dist: pre-commit>=3.0; extra == "dev"
Requires-Dist: isort>=5.12; extra == "dev"
Requires-Dist: bandit>=1.7; extra == "dev"
Requires-Dist: safety>=2.3; extra == "dev"
Provides-Extra: monitoring
Requires-Dist: prometheus-client>=0.17.0; extra == "monitoring"
Requires-Dist: grafana-api>=1.0.3; extra == "monitoring"
Requires-Dist: opentelemetry-api>=1.20.0; extra == "monitoring"
Requires-Dist: opentelemetry-sdk>=1.20.0; extra == "monitoring"
Requires-Dist: opentelemetry-instrumentation>=0.41b0; extra == "monitoring"
Provides-Extra: ml
Requires-Dist: scikit-learn>=1.3.0; extra == "ml"
Requires-Dist: tensorflow>=2.13.0; extra == "ml"
Requires-Dist: torch>=2.0.0; extra == "ml"
Requires-Dist: xgboost>=1.7.0; extra == "ml"
Requires-Dist: lightgbm>=4.0.0; extra == "ml"
Requires-Dist: optuna>=3.4.0; extra == "ml"
Provides-Extra: forex
Requires-Dist: MetaTrader5>=5.0.45; extra == "forex"
Requires-Dist: ib-insync>=0.9.86; extra == "forex"
Requires-Dist: oandapyV20>=0.6.3; extra == "forex"
Requires-Dist: fxcmpy>=1.3.0; extra == "forex"
Provides-Extra: performance
Requires-Dist: numba>=0.58.0; extra == "performance"
Requires-Dist: cython>=3.0.0; extra == "performance"
Requires-Dist: uvloop>=0.17.0; sys_platform != "win32" and extra == "performance"
Requires-Dist: orjson>=3.9.0; extra == "performance"
Provides-Extra: docs
Requires-Dist: sphinx>=7.0; extra == "docs"
Requires-Dist: sphinx-rtd-theme>=1.3; extra == "docs"
Requires-Dist: myst-parser>=2.0; extra == "docs"
Requires-Dist: sphinx-autodoc-typehints>=1.24; extra == "docs"
Provides-Extra: test
Requires-Dist: pytest>=7.0; extra == "test"
Requires-Dist: pytest-asyncio>=0.21.0; extra == "test"
Requires-Dist: pytest-cov>=4.0; extra == "test"
Requires-Dist: pytest-mock>=3.10; extra == "test"
Requires-Dist: pytest-benchmark>=4.0; extra == "test"
Requires-Dist: hypothesis>=6.82; extra == "test"
Requires-Dist: factory-boy>=3.3; extra == "test"
Provides-Extra: all
Requires-Dist: pytest>=7.0; extra == "all"
Requires-Dist: pytest-asyncio>=0.21.0; extra == "all"
Requires-Dist: pytest-cov>=4.0; extra == "all"
Requires-Dist: pytest-mock>=3.10; extra == "all"
Requires-Dist: pytest-xdist>=3.0; extra == "all"
Requires-Dist: black>=23.0; extra == "all"
Requires-Dist: ruff>=0.1.0; extra == "all"
Requires-Dist: mypy>=1.5; extra == "all"
Requires-Dist: pre-commit>=3.0; extra == "all"
Requires-Dist: isort>=5.12; extra == "all"
Requires-Dist: bandit>=1.7; extra == "all"
Requires-Dist: safety>=2.3; extra == "all"
Requires-Dist: prometheus-client>=0.17.0; extra == "all"
Requires-Dist: grafana-api>=1.0.3; extra == "all"
Requires-Dist: opentelemetry-api>=1.20.0; extra == "all"
Requires-Dist: opentelemetry-sdk>=1.20.0; extra == "all"
Requires-Dist: scikit-learn>=1.3.0; extra == "all"
Requires-Dist: tensorflow>=2.13.0; extra == "all"
Requires-Dist: torch>=2.0.0; extra == "all"
Requires-Dist: xgboost>=1.7.0; extra == "all"
Requires-Dist: MetaTrader5>=5.0.45; extra == "all"
Requires-Dist: ib-insync>=0.9.86; extra == "all"
Requires-Dist: oandapyV20>=0.6.3; extra == "all"
Requires-Dist: numba>=0.58.0; extra == "all"
Requires-Dist: uvloop>=0.17.0; sys_platform != "win32" and extra == "all"
Requires-Dist: orjson>=3.9.0; extra == "all"
